qia/__init__.py
qia/py.typed
qia-0.1.1a0.dist-info/LICENSE
qia-0.1.1a0.dist-info/WHEEL
qia-0.1.1a0.dist-info/METADATA
qia-0.1.1a0.dist-info/RECORD
