Metadata-Version: 2.1
Name: qia
Version: 0.1.1a0
Summary: Automated testing tool for Web and Mobile with Python.
License: MIT
Author: aprilahijriyan
Author-email: hijriyan23@gmail.com
Requires-Python: >=3.9,<4.0
Classifier: License :: OSI Approved :: MIT License
Classifier: Programming Language :: Python :: 3
Classifier: Programming Language :: Python :: 3.9
Classifier: Programming Language :: Python :: 3.10
Classifier: Programming Language :: Python :: 3.11
Requires-Dist: appium-python-client (>=2.8.1,<3.0.0)
Requires-Dist: behave (>=1.2.6,<2.0.0)
Requires-Dist: typer (>=0.7.0,<0.8.0)
